django_babel_underscore/__init__.py
django_babel_underscore-0.5.2.dist-info/DESCRIPTION.rst
django_babel_underscore-0.5.2.dist-info/LICENSE.txt
django_babel_underscore-0.5.2.dist-info/METADATA
django_babel_underscore-0.5.2.dist-info/RECORD
django_babel_underscore-0.5.2.dist-info/WHEEL
django_babel_underscore-0.5.2.dist-info/entry_points.txt
django_babel_underscore-0.5.2.dist-info/metadata.json
django_babel_underscore-0.5.2.dist-info/top_level.txt
