Metadata-Version: 2.0
Name: django-babel-underscore
Version: 0.5.2
Summary: Implements a underscore extractor for django-babel.
Home-page: https://github.com/EnTeQuAk/django-babel-underscore
Author: Christopher Grebs
Author-email: cg@webshox.org
License: BSD
Keywords: django-babel-underscore
Platform: UNKNOWN
Classifier: Development Status :: 2 - Pre-Alpha
Classifier: Intended Audience :: Developers
Classifier: License :: OSI Approved :: BSD License
Classifier: Natural Language :: English
Classifier: Programming Language :: Python :: 2
Classifier: Programming Language :: Python :: 2.6
Classifier: Programming Language :: Python :: 2.7
Classifier: Programming Language :: Python :: 3
Classifier: Programming Language :: Python :: 3.3
Classifier: Programming Language :: Python :: 3.4
Requires-Dist: babel (>=1.3)
Requires-Dist: django (<2.0,>=1.8)
Requires-Dist: django-babel (>=0.5.1)
Requires-Dist: markey (<0.9,>=0.8)
Provides-Extra: dev
Requires-Dist: flake8 (>=2.0); extra == 'dev'
Provides-Extra: docs
Requires-Dist: sphinx; extra == 'docs'
Provides-Extra: tests
Requires-Dist: coverage; extra == 'tests'
Requires-Dist: pytest; extra == 'tests'
Requires-Dist: pytest-cov (>=1.4); extra == 'tests'
Requires-Dist: pytest-flakes; extra == 'tests'
Requires-Dist: pytest-pep8; extra == 'tests'
Requires-Dist: python-coveralls; extra == 'tests'
